seeFretboard/NotePosition.py
seeFretboard/PitchCollection.py
seeFretboard/SeeFretboard.py
seeFretboard/__init__.py
seeFretboard/Designs/CirlceNote.py
seeFretboard/Designs/FretboardFigure.py
seeFretboard/Designs/FretboardStyle.py
seeFretboard/Designs/__init__.py
seeFretboard/GuitarSet/annotation/00_BN1-129-Eb_comp.jams
seeFretboard/GuitarSet/annotation/00_BN1-129-Eb_solo.jams
seeFretboard/GuitarSet/annotation/00_BN1-147-Gb_comp.jams
seeFretboard/GuitarSet/annotation/00_BN1-147-Gb_solo.jams
seeFretboard/GuitarSet/annotation/00_BN2-131-B_comp.jams
seeFretboard/GuitarSet/annotation/00_BN2-131-B_solo.jams
seeFretboard/GuitarSet/annotation/00_BN2-166-Ab_comp.jams
seeFretboard/GuitarSet/annotation/00_BN2-166-Ab_solo.jams
seeFretboard/GuitarSet/annotation/00_BN3-119-G_comp.jams
seeFretboard/GuitarSet/annotation/00_BN3-119-G_solo.jams
seeFretboard/GuitarSet/annotation/00_BN3-154-E_comp.jams
seeFretboard/GuitarSet/annotation/00_BN3-154-E_solo.jams
seeFretboard/GuitarSet/annotation/00_Funk1-114-Ab_comp.jams
seeFretboard/GuitarSet/annotation/00_Funk1-114-Ab_solo.jams
seeFretboard/GuitarSet/annotation/00_Funk1-97-C_comp.jams
seeFretboard/GuitarSet/annotation/00_Funk1-97-C_solo.jams
seeFretboard/GuitarSet/annotation/00_Funk2-108-Eb_comp.jams
seeFretboard/GuitarSet/annotation/00_Funk2-108-Eb_solo.jams
seeFretboard/GuitarSet/annotation/00_Funk2-119-G_comp.jams
seeFretboard/GuitarSet/annotation/00_Funk2-119-G_solo.jams
seeFretboard/GuitarSet/annotation/00_Funk3-112-C#_comp.jams
seeFretboard/GuitarSet/annotation/00_Funk3-112-C#_solo.jams
seeFretboard/GuitarSet/annotation/00_Funk3-98-A_comp.jams
seeFretboard/GuitarSet/annotation/00_Funk3-98-A_solo.jams
seeFretboard/GuitarSet/annotation/00_Jazz1-130-D_comp.jams
seeFretboard/GuitarSet/annotation/00_Jazz1-130-D_solo.jams
seeFretboard/GuitarSet/annotation/00_Jazz1-200-B_comp.jams
seeFretboard/GuitarSet/annotation/00_Jazz1-200-B_solo.jams
seeFretboard/GuitarSet/annotation/00_Jazz2-110-Bb_comp.jams
seeFretboard-0.1.5.5.dist-info/LICENSE
seeFretboard-0.1.5.5.dist-info/METADATA
seeFretboard-0.1.5.5.dist-info/WHEEL
seeFretboard-0.1.5.5.dist-info/top_level.txt
seeFretboard-0.1.5.5.dist-info/RECORD
