Metadata-Version: 2.1
Name: seeFretboard
Version: 0.1.5.5
Summary: For Release
Home-page: https://github.com/LindaRZhang/seeFretboard
Author: Linda Rong Zhang
Author-email: ronglindaz@gmail.com
License: GNU
Project-URL: Bug Tracker, https://github.com/LindaRZhang/seeFretboard/issues
License-File: LICENSE
Requires-Dist: requests
